twittersphere/__init__.py
twittersphere/_schema.py
twittersphere/cli.py
twittersphere/db.py
twittersphere/process.py
twittersphere/twittersphere.py
twittersphere-0.4.0.dist-info/LICENSE
twittersphere-0.4.0.dist-info/METADATA
twittersphere-0.4.0.dist-info/WHEEL
twittersphere-0.4.0.dist-info/entry_points.txt
twittersphere-0.4.0.dist-info/top_level.txt
twittersphere-0.4.0.dist-info/RECORD
