Metadata-Version: 2.1
Name: twittersphere
Version: 0.4.0
Summary: Tools for content based filtering of tweets and Twitter accounts
Home-page: https://github.com/QUT-Digital-Observatory/twittersphere
Author: Sam Hames and QUT Digital Observatory
Author-email: s.hames@uq.edu.au
License: MIT
Keywords: social_science social_media_analysis
Classifier: Programming Language :: Python :: 3
Classifier: License :: OSI Approved :: MIT License
Classifier: Operating System :: OS Independent
Classifier: Development Status :: 4 - Beta
Classifier: Environment :: Console
Classifier: Intended Audience :: Science/Research
Classifier: Topic :: Scientific/Engineering :: Information Analysis
Classifier: Topic :: Sociology
Requires-Python: >=3.9
License-File: LICENSE
Requires-Dist: click (>=8.0.0)
Requires-Dist: regex (>=2021.3.17)
Requires-Dist: glom (>=22.1.0)
